timezone/__init__.py
timezone/admin.py
timezone/middleware.py
timezone/models.py
timezone/migrations/0001_initial.py
timezone/migrations/0002_default_utc.py
timezone/migrations/__init__.py
django_user_timezone-0.1.0.dist-info/METADATA
django_user_timezone-0.1.0.dist-info/WHEEL
django_user_timezone-0.1.0.dist-info/entry_points.txt
django_user_timezone-0.1.0.dist-info/top_level.txt
django_user_timezone-0.1.0.dist-info/RECORD
