Metadata-Version: 2.4
Name: django-user-timezone
Version: 0.1.0
Summary: Quick Timezone code
License-Expression: MIT
Project-URL: source, https://codeberg.org/kfdm/django-user-timezone
Project-URL: issues, https://codeberg.org/kfdm/django-user-timezone/issues
Classifier: Development Status :: 3 - Alpha
Classifier: Framework :: Django :: 4.2
Classifier: Framework :: Django :: 5.0
Classifier: Framework :: Django :: 5.1
Classifier: Framework :: Django :: 5.2
Classifier: Framework :: Django :: 6.0
Classifier: Framework :: Django
Classifier: Natural Language :: English
Classifier: Operating System :: OS Independent
Classifier: Programming Language :: Python :: 3.10
Classifier: Programming Language :: Python :: 3.11
Classifier: Programming Language :: Python :: 3.12
Classifier: Programming Language :: Python :: 3.13
Classifier: Programming Language :: Python :: 3.14
Classifier: Programming Language :: Python :: 3.15
Classifier: Programming Language :: Python :: 3.9
Classifier: Programming Language :: Python
Requires-Python: >=3.9
Requires-Dist: django>=4.2
